{"id":"3y12i7xrbl8hk7yneo0d5ra","title":"Get All That Network Activity Under Control with Priority Hints","desc":"","updated":1695267424965,"created":1695267290514,"custom":{},"fname":"dev.web.performance.priority-hints","type":"note","vault":{"fsPath":"vault"},"contentHash":"c841c88294816348ea9f9d4ca70cd449","links":[],"anchors":{"prioritizing-preloaded-assets":{"type":"header","text":"Prioritizing Preloaded Assets","value":"prioritizing-preloaded-assets","line":20,"column":0,"depth":2},"when-to-use-it":{"type":"header","text":"When to Use It","value":"when-to-use-it","line":65,"column":0,"depth":3},"prioritizing-fetch-requests":{"type":"header","text":"Prioritizing fetch() Requests","value":"prioritizing-fetch-requests","line":69,"column":0,"depth":2},"useful-counterpart-keepalive-true":{"type":"header","text":"Useful counterpart: keepalive: true","value":"useful-counterpart-keepalive-true","line":113,"column":0,"depth":4},"when-to-use-it-1":{"type":"header","text":"When to Use It","value":"when-to-use-it-1","line":119,"column":0,"depth":3},"prioritizing-img--requests":{"type":"header","text":"Prioritizing <img /> Requests","value":"prioritizing-img--requests","line":123,"column":0,"depth":2},"when-to-use-it-2":{"type":"header","text":"When to Use It","value":"when-to-use-it-2","line":161,"column":0,"depth":3},"prioritizing-script--tags":{"type":"header","text":"Prioritizing <script /> Tags","value":"prioritizing-script--tags","line":165,"column":0,"depth":2},"non-blocking-but-high-priority-scripts":{"type":"header","text":"Non-Blocking, but High-Priority Scripts","value":"non-blocking-but-high-priority-scripts","line":185,"column":0,"depth":3},"when-to-use-it-3":{"type":"header","text":"When to Use It","value":"when-to-use-it-3","line":209,"column":0,"depth":3},"to-be-used-intentionally":{"type":"header","text":"To Be Used Intentionally","value":"to-be-used-intentionally","line":213,"column":0,"depth":2},"reviewing-when-to-hint":{"type":"header","text":"Reviewing: When to Hint","value":"reviewing-when-to-hint","line":223,"column":0,"depth":2},"make-the-browser-guess-less":{"type":"header","text":"Make the Browser Guess Less","value":"make-the-browser-guess-less","line":232,"column":0,"depth":2}},"children":[],"parent":"pa1bstln0xt54o30z6taebc","data":{}}
