{"id":"58eyi3pp8fqbweyarzd45w5","title":"Meditation","desc":"","updated":1674898707310,"created":1651626731291,"custom":{},"fname":"well-being.meditation","type":"note","vault":{"fsPath":"vault"},"contentHash":"5534c42fdab943aabd27f4e7f8bf4267","links":[{"type":"wiki","from":{"fname":"well-being.meditation","id":"58eyi3pp8fqbweyarzd45w5","vaultName":"vault"},"value":"life-tips.shut-off","position":{"start":{"line":2,"column":3,"offset":3},"end":{"line":2,"column":25,"offset":25},"indent":[]},"xvault":false,"sameFile":false,"to":{"fname":"life-tips.shut-off"}}],"anchors":{},"children":[],"parent":"hjNeNc1F2JUh0lTWanH4h","data":{}}
