{"id":"b6u18z9o90yxv9ww6d2jd54","title":"A practical guide to using shadow DOM","desc":"","updated":1709705872688,"created":1709705567431,"custom":{},"fname":"dev.html.declarative-shadow-dom-guide","type":"note","vault":{"fsPath":"vault"},"contentHash":"5394532025004069b30164d6af23ab7b","links":[],"anchors":{"what-the-heck-is-shadow-dom":{"type":"header","text":"What the heck is “shadow DOM”?","value":"what-the-heck-is-shadow-dom","line":10,"column":0,"depth":2},"imperative-vs-declarative":{"type":"header","text":"“Imperative” vs “declarative”","value":"imperative-vs-declarative","line":24,"column":0,"depth":2},"use-cases":{"type":"header","text":"Use cases","value":"use-cases","line":58,"column":0,"depth":2},"style-scoping-and-cascading":{"type":"header","text":"Style scoping and cascading","value":"style-scoping-and-cascading","line":84,"column":0,"depth":2},"shadow-dom-is-still-problematic":{"type":"header","text":"Shadow DOM is still problematic","value":"shadow-dom-is-still-problematic","line":142,"column":0,"depth":2},"usage-within-frameworks":{"type":"header","text":"Usage within frameworks","value":"usage-within-frameworks","line":168,"column":0,"depth":2}},"children":[],"parent":"J5O6LCmOghKhFwQFKeoow","data":{}}
