{"id":"dvjc48q2a8tm8n0yvqtgylf","title":"React I Love You, But You're Bringing Me Down","desc":"","updated":1663734714975,"created":1663718149852,"custom":{},"fname":"dev.javascript.react.react-i-love-you","type":"note","vault":{"fsPath":"vault"},"contentHash":"0352252f4dc8735ad1d64beb559a9639","links":[],"anchors":{"you-were-the-one":{"type":"header","text":"You Were The One","value":"you-were-the-one","line":19,"column":0,"depth":2},"heroes-of-new-forms":{"type":"header","text":"Heroes Of New Forms","value":"heroes-of-new-forms","line":29,"column":0,"depth":2},"youre-too-context-sensitive":{"type":"header","text":"You're Too Context Sensitive","value":"youre-too-context-sensitive","line":86,"column":0,"depth":2},"i-want-none-of-this":{"type":"header","text":"I Want None Of This","value":"i-want-none-of-this","line":165,"column":0,"depth":2},"the-butterfly-use-effect":{"type":"header","text":"The Butterfly (use) Effect","value":"the-butterfly-use-effect","line":196,"column":0,"depth":2},"makeup-your-mind":{"type":"header","text":"Makeup Your Mind","value":"makeup-your-mind","line":345,"column":0,"depth":2},"strict-machine":{"type":"header","text":"Strict Machine","value":"strict-machine","line":374,"column":0,"depth":2},"youve-been-gone-too-long":{"type":"header","text":"You've Been Gone Too Long","value":"youve-been-gone-too-long","line":422,"column":0,"depth":2},"family-affair":{"type":"header","text":"Family Affair","value":"family-affair","line":483,"column":0,"depth":2},"its-not-me-its-you":{"type":"header","text":"It's Not Me, It's You","value":"its-not-me-its-you","line":493,"column":0,"depth":2},"hacker-news":{"type":"header","text":"Hacker News","value":"hacker-news","line":499,"column":0,"depth":1},"bilalbudhani":{"type":"header","text":"BilalBudhani","value":"bilalbudhani","line":501,"column":0,"depth":2},"buscoquadnary":{"type":"header","text":"buscoquadnary","value":"buscoquadnary","line":513,"column":0,"depth":3},"bilalbudhani-1":{"type":"header","text":"BilalBudhani","value":"bilalbudhani-1","line":525,"column":0,"depth":4},"gherkinnn":{"type":"header","text":"gherkinnn","value":"gherkinnn","line":531,"column":0,"depth":2},"mmis1000":{"type":"header","text":"mmis1000","value":"mmis1000","line":538,"column":0,"depth":3},"kronislv":{"type":"header","text":"KronisLV","value":"kronislv","line":553,"column":0,"depth":4},"mmis1000-1":{"type":"header","text":"mmis1000","value":"mmis1000-1","line":578,"column":0,"depth":4},"throwaway284534":{"type":"header","text":"throwaway284534","value":"throwaway284534","line":592,"column":0,"depth":1},"nophunphil":{"type":"header","text":"nophunphil","value":"nophunphil","line":601,"column":0,"depth":2},"egeozcan":{"type":"header","text":"egeozcan","value":"egeozcan","line":607,"column":0,"depth":3},"fabian2k":{"type":"header","text":"fabian2k","value":"fabian2k","line":611,"column":0,"depth":2},"joshribakoff":{"type":"header","text":"joshribakoff","value":"joshribakoff","line":617,"column":0,"depth":2},"sergiotapia":{"type":"header","text":"sergiotapia","value":"sergiotapia","line":623,"column":0,"depth":2},"azemetre":{"type":"header","text":"azemetre","value":"azemetre","line":629,"column":0,"depth":3},"jnsaff2":{"type":"header","text":"jnsaff2","value":"jnsaff2","line":633,"column":0,"depth":4},"krnsi":{"type":"header","text":"krnsi","value":"krnsi","line":638,"column":0,"depth":4},"sergiotapia-1":{"type":"header","text":"sergiotapia","value":"sergiotapia-1","line":642,"column":0,"depth":4}},"children":[],"parent":"0gqmdqmd5rylcs3ljzwsww4","data":{}}
