{"id":"j0N1aVKxe96dktmyADG9U","title":"Software Engineering","desc":"","updated":1758238626834,"created":1645514209965,"custom":{},"fname":"dev.software-engineering","type":"note","vault":{"fsPath":"vault"},"contentHash":"4d14d0e54d1e8dd83617dded426b43bd","links":[{"type":"wiki","from":{"fname":"dev.software-engineering","id":"j0N1aVKxe96dktmyADG9U","vaultName":"vault"},"value":"tags.bookmark","alias":"#bookmark","position":{"start":{"line":16,"column":112,"offset":1354},"end":{"line":16,"column":121,"offset":1363},"indent":[]},"xvault":false,"to":{"fname":"tags.bookmark"}}],"anchors":{"collections":{"type":"header","text":"Collections","value":"collections","line":8,"column":0,"depth":2},"modeling":{"type":"header","text":"Modeling","value":"modeling","line":72,"column":0,"depth":2},"you-cant-buy-integration":{"type":"header","text":"You Can't Buy Integration","value":"you-cant-buy-integration","line":81,"column":0,"depth":2},"dont-call-yourself-a-programmer-and-other-career-advice":{"type":"header","text":"Don't Call Yourself A Programmer, And Other Career Advice","value":"dont-call-yourself-a-programmer-and-other-career-advice","line":85,"column":0,"depth":2},"eight-tips-to-write-functions-like-a-senior-developer":{"type":"header","text":"Eight tips to Write Functions like a Senior Developer","value":"eight-tips-to-write-functions-like-a-senior-developer","line":91,"column":0,"depth":2},"architecture":{"type":"header","text":"Architecture","value":"architecture","line":98,"column":0,"depth":2},"thread-per-core":{"type":"header","text":"Thread-per-core","value":"thread-per-core","line":118,"column":0,"depth":3},"algorithms":{"type":"header","text":"Algorithms","value":"algorithms","line":124,"column":0,"depth":2},"hexagonal-grids":{"type":"header","text":"Hexagonal Grids","value":"hexagonal-grids","line":126,"column":0,"depth":3},"approximate-timing-for-various-operations-on-a-typical-pc":{"type":"header","text":"Approximate timing for various operations on a typical PC","value":"approximate-timing-for-various-operations-on-a-typical-pc","line":134,"column":0,"depth":2},"crypto":{"type":"header","text":"Crypto","value":"crypto","line":138,"column":0,"depth":2}},"children":["ndzzrqq15oi71pbemlkqse3","2az7jx1wd9guc66l1cdb54j","x8ialsmpsu1udfkifxlitql","97ha3zf4db021vg7p1jtby7","6lhj3c2ssl5vhunnbtfvdui","3qd6qjev0hbwuzw47h96vee","7jdxj17k3fj5r6l4zuqdx57","kkmhbz67acbzr5hxrw1cbxa","80dlg24o2sdu3ti1ipwlgcb","bpw92y9ez0959qtnaedllfs","o2xgz8c6d9xn3at1rjymbnw","7uuid3nck5c8r1ngjm8o254","6hmmfse40un0yvyhcfhf1kh","p54hilx39w0qha68frckomu","cdve3pqbh1ftajzj8uu0get","h4bdthyszcjle90ytec22xp","c00nsizm5rcb32jay5z3ifm","a48cslm3wj5bpq04rrkzrhx","e3yxr6ae8tfu2hzmbi70rzc","tgud80cj6687x0o11ht4sn6","bmkxxriirn5e6ajhyzpiqtb","2xg6iqfwi5i0aceu5y7d1h2"],"parent":"ZbdkdApFqLdks4Moq92R9","data":{}}
