{"id":"qe9k5ss6me8btz4h021n18d","title":"Cache your CORS, for performance & profit","desc":"","updated":1663655438497,"created":1663655222365,"custom":{},"fname":"dev.web.performance.cache-your-cors","type":"note","vault":{"fsPath":"vault"},"contentHash":"c3137f2cda075e41080f71adee666f47","links":[],"anchors":{"what-are-cors-preflight-requests":{"type":"header","text":"What are CORS preflight requests?","value":"what-are-cors-preflight-requests","line":16,"column":0,"depth":2},"why-is-this-bad":{"type":"header","text":"Why is this bad?","value":"why-is-this-bad","line":42,"column":0,"depth":2},"how-can-you-cache-preflight-responses":{"type":"header","text":"How can you cache preflight responses?","value":"how-can-you-cache-preflight-responses","line":56,"column":0,"depth":2},"cors-caching-for-browsers":{"type":"header","text":"CORS caching for browsers","value":"cors-caching-for-browsers","line":63,"column":0,"depth":3},"caching-for-cdnscors":{"type":"header","text":"caching for CDNsCORS","value":"caching-for-cdnscors","line":75,"column":0,"depth":3},"configuration-examples":{"type":"header","text":"Configuration examples","value":"configuration-examples","line":104,"column":0,"depth":2},"caching-cors-with-aws-lambda":{"type":"header","text":"Caching CORS with AWS Lambda","value":"caching-cors-with-aws-lambda","line":108,"column":0,"depth":3},"caching-cors-in-nodejs":{"type":"header","text":"Caching CORS in Node.js","value":"caching-cors-in-nodejs","line":154,"column":0,"depth":3},"caching-cors-in-python":{"type":"header","text":"Caching CORS in Python","value":"caching-cors-in-python","line":183,"column":0,"depth":3},"caching-cors-with-java-spring":{"type":"header","text":"Caching CORS with Java Spring","value":"caching-cors-with-java-spring","line":191,"column":0,"depth":3},"hacker-news":{"type":"header","text":"Hacker News","value":"hacker-news","line":222,"column":0,"depth":1}},"children":[],"parent":"pa1bstln0xt54o30z6taebc","data":{}}
