{"id":"sifjdlyh7vc7t98zi4y8ydq","title":"Tips for typing import statements in JavaScript","desc":"","updated":1670459913629,"created":1670459855775,"custom":{},"fname":"dev.tools.vs-code.typing-import-statements","type":"note","vault":{"fsPath":"vault"},"contentHash":"98ec9e9459b9aa2666d7609a2329ef95","links":[],"anchors":{"does-javascripts-import-statement-have-the-wrong-syntax":{"type":"header","text":"Does JavaScript’s import statement have the wrong syntax?  #","value":"does-javascripts-import-statement-have-the-wrong-syntax","line":14,"column":0,"depth":2},"auto-importing":{"type":"header","text":"Auto-importing  #","value":"auto-importing","line":39,"column":0,"depth":2},"manually-typing-import-statements":{"type":"header","text":"Manually typing import statements  #","value":"manually-typing-import-statements","line":50,"column":0,"depth":2},"a-code-snippet-for-faster-entry":{"type":"header","text":"A code snippet for faster entry  #","value":"a-code-snippet-for-faster-entry","line":66,"column":0,"depth":2},"further-reading":{"type":"header","text":"Further reading  #","value":"further-reading","line":106,"column":0,"depth":2}},"children":[],"parent":"ncyn8xow2x0rfon0mjy0bnc","data":{}}
