{"id":"V2Jt0WU66kh2siiIUoeLS","title":"Security tools","desc":"","updated":1756077709130,"created":1644825770935,"custom":{},"fname":"dev.security.tools","type":"note","vault":{"fsPath":"vault"},"contentHash":"d5257422dbd367140c31ee0802646d79","links":[],"anchors":{"collections":{"type":"header","text":"Collections","value":"collections","line":8,"column":0,"depth":2},"misc":{"type":"header","text":"Misc","value":"misc","line":17,"column":0,"depth":2},"bitwarden---error-failed-to-fetch-in-chrome":{"type":"header","text":"Bitwarden - Error “Failed to fetch” in Chrome","value":"bitwarden---error-failed-to-fetch-in-chrome","line":19,"column":0,"depth":3}},"children":["ntv9jsdm9vei4te6wd9dvls"],"parent":"NXAefr1pIXFjCcemglCJM","data":{}}
