{"id":"vjfxdfsvtufatxarr0llqjf","title":"Anchor Tag","desc":"","updated":1700011817071,"created":1700011775950,"custom":{},"fname":"dev.web.a11y.anchor-tag","type":"note","vault":{"fsPath":"vault"},"contentHash":"bbf582d9802522738ae3399b9113280a","links":[],"anchors":{"clicking-a-element-using-enterspace-key-is-not-working-even-though-it-is-focused-accessibility":{"type":"header","text":"Clicking <a> element using Enter/Space key is not working even though it is focused (accessibility)","value":"clicking-a-element-using-enterspace-key-is-not-working-even-though-it-is-focused-accessibility","line":8,"column":0,"depth":2},"short-answer":{"type":"header","text":"Short Answer","value":"short-answer","line":10,"column":0,"depth":3},"longer-answer":{"type":"header","text":"Longer Answer","value":"longer-answer","line":16,"column":0,"depth":3},"so-what-should-i-use":{"type":"header","text":"So what should I use?","value":"so-what-should-i-use","line":28,"column":0,"depth":4},"why-does-it-matter":{"type":"header","text":"Why does it matter?","value":"why-does-it-matter","line":34,"column":0,"depth":3},"so-how-to-call-a-function-from-a-page":{"type":"header","text":"So how to call a function from a page?","value":"so-how-to-call-a-function-from-a-page","line":46,"column":0,"depth":3},"but-i-need-to-do-something-before-navigation-occurs":{"type":"header","text":"But I need to do something before navigation occurs?","value":"but-i-need-to-do-something-before-navigation-occurs","line":72,"column":0,"depth":3}},"children":[],"parent":"7tPeWrJHQmeiMg4HWoymw","data":{}}
